LICENSE
MANIFEST.in
README.rst
setup.py
env36/lib/python3.6/site-packages/Cython/Debugger/Tests/cfuncs.c
env36/lib/python3.6/site-packages/Cython/Utility/AsyncGen.c
env36/lib/python3.6/site-packages/Cython/Utility/Buffer.c
env36/lib/python3.6/site-packages/Cython/Utility/Builtins.c
env36/lib/python3.6/site-packages/Cython/Utility/CMath.c
env36/lib/python3.6/site-packages/Cython/Utility/Capsule.c
env36/lib/python3.6/site-packages/Cython/Utility/CommonStructures.c
env36/lib/python3.6/site-packages/Cython/Utility/Complex.c
env36/lib/python3.6/site-packages/Cython/Utility/Coroutine.c
env36/lib/python3.6/site-packages/Cython/Utility/CythonFunction.c
env36/lib/python3.6/site-packages/Cython/Utility/Embed.c
env36/lib/python3.6/site-packages/Cython/Utility/Exceptions.c
env36/lib/python3.6/site-packages/Cython/Utility/ExtensionTypes.c
env36/lib/python3.6/site-packages/Cython/Utility/FunctionArguments.c
env36/lib/python3.6/site-packages/Cython/Utility/ImportExport.c
env36/lib/python3.6/site-packages/Cython/Utility/MemoryView_C.c
env36/lib/python3.6/site-packages/Cython/Utility/ModuleSetupCode.c
env36/lib/python3.6/site-packages/Cython/Utility/ObjectHandling.c
env36/lib/python3.6/site-packages/Cython/Utility/Optimize.c
env36/lib/python3.6/site-packages/Cython/Utility/Overflow.c
env36/lib/python3.6/site-packages/Cython/Utility/Printing.c
env36/lib/python3.6/site-packages/Cython/Utility/Profile.c
env36/lib/python3.6/site-packages/Cython/Utility/StringTools.c
env36/lib/python3.6/site-packages/Cython/Utility/TestUtilityLoader.c
env36/lib/python3.6/site-packages/Cython/Utility/TypeConversion.c
env36/lib/python3.6/site-packages/Cython/Utility/arrayarray.h
env36/lib/python3.6/site-packages/numpy/core/include/numpy/__multiarray_api.h
env36/lib/python3.6/site-packages/numpy/core/include/numpy/__ufunc_api.h
env36/lib/python3.6/site-packages/numpy/core/include/numpy/_neighborhood_iterator_imp.h
env36/lib/python3.6/site-packages/numpy/core/include/numpy/_numpyconfig.h
thinc_gpu_ops.egg-info/PKG-INFO
thinc_gpu_ops.egg-info/SOURCES.txt
thinc_gpu_ops.egg-info/dependency_links.txt
thinc_gpu_ops.egg-info/not-zip-safe
thinc_gpu_ops.egg-info/requires.txt
thinc_gpu_ops.egg-info/top_level.txt